hockey_scraper/__init__.py
hockey_scraper/cli.py
hockey_scraper/nhl/__init__.py
hockey_scraper/nhl/game_scraper.py
hockey_scraper/nhl/json_schedule.py
hockey_scraper/nhl/live_scrape.py
hockey_scraper/nhl/playing_roster.py
hockey_scraper/nhl/scrape_functions.py
hockey_scraper/nhl/pbp/__init__.py
hockey_scraper/nhl/pbp/espn_pbp.py
hockey_scraper/nhl/pbp/html_pbp.py
hockey_scraper/nhl/pbp/json_pbp.py
hockey_scraper/nhl/shifts/__init__.py
hockey_scraper/nhl/shifts/html_shifts.py
hockey_scraper/nhl/shifts/json_shifts.py
hockey_scraper/nwhl/__init__.py
hockey_scraper/nwhl/game_pbp.py
hockey_scraper/nwhl/scrape_functions.py
hockey_scraper/nwhl/scrape_schedule.py
hockey_scraper/utils/__init__.py
hockey_scraper/utils/config.py
hockey_scraper/utils/merge_pbp_shifts.py
hockey_scraper/utils/player_name_fixes.json
hockey_scraper/utils/save_pages.py
hockey_scraper/utils/shared.py
hockey_scraper/utils/team_tri_codes.json
hockey_scraper/utils/tri_code_conversion.json
tests/__init__.py
tests/test_espn_pbp.py
tests/test_game_scraper.py
tests/test_html_pbp.py
tests/test_html_shifts.py
tests/test_json_pbp.py
tests/test_json_schedule.py
tests/test_json_shifts.py
tests/test_nwhl.py
tests/test_playing_roster.py
tests/test_scrape_functions.py
tests/test_shared.py
hockey_scraper-1.40.3.dist-info/LICENSE.txt
hockey_scraper-1.40.3.dist-info/METADATA
hockey_scraper-1.40.3.dist-info/WHEEL
hockey_scraper-1.40.3.dist-info/top_level.txt
hockey_scraper-1.40.3.dist-info/RECORD
