Metadata-Version: 2.1
Name: hockey-scraper
Version: 1.40.3
Summary: Python Package for scraping NHL Play-by-Play and Shift data.
Home-page: https://github.com/HarryShomer/Hockey-Scraper
Author: Harry Shomer
Author-email: Harryshomer@gmail.com
License: GNU General Public License v3 (GPLv3)
Keywords: NHL
Classifier: Development Status :: 5 - Production/Stable
Classifier: Programming Language :: Python :: 3
Classifier: Programming Language :: Python :: 2
License-File: LICENSE.txt
Requires-Dist: BeautifulSoup4
Requires-Dist: requests
Requires-Dist: lxml
Requires-Dist: html5lib
Requires-Dist: pandas
Requires-Dist: pytest
Requires-Dist: pytz
Requires-Dist: tqdm
